mas/__init__.py
mas/__main__.py
mas/__version__.py
mas/agent.py
mas/cli.py
mas/logger.py
mas/protocol.py
mas/redis_client.py
mas/redis_types.py
mas/runner.py
mas/server.py
mas/state.py
mas/_proto/__init__.py
mas/_proto/v1/__init__.py
mas/_proto/v1/mas_pb2.py
mas/_proto/v1/mas_pb2.pyi
mas/_proto/v1/mas_pb2_grpc.py
mas/gateway/__init__.py
mas/gateway/audit.py
mas/gateway/authorization.py
mas/gateway/circuit_breaker.py
mas/gateway/config.py
mas/gateway/dlp.py
mas/gateway/rate_limit.py
mas_framework-0.4.2.dist-info/METADATA
mas_framework-0.4.2.dist-info/WHEEL
mas_framework-0.4.2.dist-info/entry_points.txt
mas_framework-0.4.2.dist-info/licenses/LICENSE
mas_framework-0.4.2.dist-info/RECORD
