Metadata-Version: 2.4
Name: mas-framework
Version: 0.4.2
Summary: A Multi-Agent System Framework
Author-email: Lemuel Boyce <lemuel@vokality.com>
License: MIT
License-File: LICENSE
Keywords: AI,agent,framework,multi-agent
Classifier: Development Status :: 1 - Planning
Classifier: Intended Audience :: Developers
Classifier: License :: OSI Approved :: MIT License
Classifier: Programming Language :: Python :: 3.14
Classifier: Topic :: Software Development :: Libraries :: Application Frameworks
Classifier: Topic :: Software Development :: Libraries :: Python Modules
Requires-Python: >=3.13
Requires-Dist: grpcio>=1.76.0
Requires-Dist: protobuf>=6.33.5
Requires-Dist: pydantic-settings>=2.0.0
Requires-Dist: pydantic>=2.12.3
Requires-Dist: pyyaml>=6.0
Requires-Dist: redis[hiredis]>=7.1.0
